automatix/__init__.py
automatix/automata/__init__.py
automatix/automata/nfa.py
automatix/automata/strel.py
automatix/operators/__init__.py
automatix/operators/matrix.py
automatix/operators/polynomial.py
automatix/py.typed
automatix/spec.py
automatix/weights/__init__.py
automatix/weights/guard_weights.py
argus_automatix-0.5.1.dist-info/WHEEL
argus_automatix-0.5.1.dist-info/METADATA
argus_automatix-0.5.1.dist-info/RECORD
