Metadata-Version: 2.3
Name: argus-automatix
Version: 0.5.1
Summary: Symbolic (weighted) automata monitors
Author: Anand Balakrishnan
Author-email: Anand Balakrishnan <anandbala1597@gmail.com>
Requires-Dist: jax>=0.8
Requires-Dist: jaxtyping>=0.3
Requires-Dist: equinox>=0.12
Requires-Dist: optree>=0.17.0
Requires-Dist: bitarray>=3.8.0
Requires-Dist: attrs>=25.4.0
Requires-Dist: networkx
Requires-Dist: numpy
Requires-Dist: typing-extensions
Requires-Dist: types-networkx
Requires-Dist: logic-asts>=1.4.1
Requires-Dist: algebraic-jax>=1.0.0
Requires-Dist: morphata>=1.0.0
Requires-Python: >=3.12
